{
  "SAMPLE_ID": "ORD-1762495-01",
  "MRN": "ORD-1762495-01",
  "BIRTH_DATE": "Fri, 30 Dec 1966 10:00:00 GMT",
  "GENDER": "Female",
  "ONCOTREE_PRIMARY_DIAGNOSIS_NAME": "Non-Small Cell Lung Cancer",
  "ONCOTREE_PRIMARY_DIAGNOSIS": "Non-Small Cell Lung Cancer",
  "PATHOLOGIST_NAME": "Not Provided",
  "REPORT_DATE": "Sat, 18 Nov 2023 10:00:00 GMT",
  "TUMOR_MUTATIONAL_BURDEN_PER_MEGABASE": 4.83,
  "MMR_STATUS": "Proficient (MMR-P / MSS)",
  "FIRST_NAME": "NA",
  "LAST_NAME": "NA",
  "ORD_PHYSICIAN_EMAIL": "NA",
  "PANEL_VERSION": 0,
  "REPORT_VERSION": "0",
  "VITAL_STATUS": "alive",
  "TEST_NAME": "oncopanel"
}